[
  {
    "_id": "Для Собак",
    "path": "Товари для собак"
  },
  {
    "_id": "Для Котів",
    "path": "Товари для кішок"
  },
  {
    "_id": "Для Собак,Корм та Смаколики",
    "path": "Товари для собак,Корм для собак"
  },

  {
    "_id": {
      "Кішок": "Для Котів,Догляд та Гігієна",
      "Котів": "Для Котів,Догляд та Гігієна",
      "Собак": "Для Собак,Догляд та Гігієна"
    },
    "path": "Догляд та гігієна"
  },

  {
    "_id": {
      "Кішок": "Для Котів,Ветпрепарати",
      "Котів": "Для Котів,Ветпрепарати",
      "Собак": "Для Собак,Ветпрепарати"
    },
    "path": "ветпрепарати"
  },

  {
    "_id": {
      "Кішок": "Для Котів,Вітаміни",
      "Котів": "Для Котів,Вітаміни",
      "Собак": "Для Собак,Вітаміни"
    },
    "path": "вітаміни"
  },

  {
    "_id": {
      "Кішок": "Для Котів,Одяг та Аксесуари",
      "Котів": "Для Котів,Одяг та Аксесуари",
      "Собак": "Для Собак,Одяг та Аксесуари"
    },
    "path": "одяг для тварин"
  },

  {
    "_id": {
      "Кішок": "Для Котів,Іграшки",
      "Котів": "Для Котів,Іграшки",
      "Собак": "Для Собак,Іграшки"
    },
    "path": "іграшки"
  },

  {
    "_id": {
      "Гризунів": "Для Гризунів,Наповнювачі",
      "Птахів": "Для Птахів,Наповнювачі",
      "Кішок": "Для Котів,Туалетні наповнювачі",
      "Котів": "Для Котів,Туалетні наповнювачі"
    },
    "path": "наповнювачі"
  },

  {
    "_id": {
      "Кішок": "Для Котів,Спальні місця та перенесення",
      "Котів": "Для Котів,Спальні місця та перенесення",
      "Собак": "Для Собак,Спальні місця та перенесення"
    },
    "path": "спальні місця"
  },

  {
    "_id": "Для Котів,Туалети",
    "path": "туалети"
  },

  {
    "_id": "65a39ee40c56566a2624f7d2",
    "path": "Рослини і догляд за ними"
  },
  {
    "_id": "65a39ee40c56566a2624f7d3",
    "path": "Рослини і догляд за ними,Субстрати і ґрунти для рослин"
  },
  {
    "_id": "65a39ee40c56566a2624f7d4",
    "path": "Рослини і догляд за ними,Субстрати і ґрунти для рослин,Для бегонії"
  },
  {
    "_id": "65a39ee40c56566a2624f7d5",
    "path": "Рослини і догляд за ними,Субстрати і ґрунти для рослин,Для газонів"
  },
  {
    "_id": "65a39ee40c56566a2624f7d6",
    "path": "Рослини і догляд за ними,Субстрати і ґрунти для рослин,Для декоративно-листяних рослин"
  },
  {
    "_id": "65a39ee40c56566a2624f7d7",
    "path": "Рослини і догляд за ними,Субстрати і ґрунти для рослин,Для кактусів"
  },
  {
    "_id": "65a39ee40c56566a2624f7d8",
    "path": "Рослини і догляд за ними,Субстрати і ґрунти для рослин,Для квітучих рослин"
  },
  {
    "_id": "65a39ee40c56566a2624f7d9",
    "path": "Рослини і догляд за ними,Субстрати і ґрунти для рослин,Для кімнатних рослин"
  },
  {
    "_id": "65a39ee40c56566a2624f7da",
    "path": "Рослини і догляд за ними,Субстрати і ґрунти для рослин,Для листяних дерев і чагарників"
  },
  {
    "_id": "65a39ee40c56566a2624f7db",
    "path": "Рослини і догляд за ними,Субстрати і ґрунти для рослин,Для овочевих культур"
  },
  {
    "_id": "65a39ee40c56566a2624f7dc",
    "path": "Рослини і догляд за ними,Субстрати і ґрунти для рослин,Для пальм"
  },
  {
    "_id": "65a39ee40c56566a2624f7dd",
    "path": "Рослини і догляд за ними,Субстрати і ґрунти для рослин,Для пеларгоній"
  },
  {
    "_id": "65a39ee40c56566a2624f7de",
    "path": "Рослини і догляд за ними,Субстрати і ґрунти для рослин,Для плодово-ягідних рослин"
  },
  {
    "_id": "65a39ee40c56566a2624f7df",
    "path": "Рослини і догляд за ними,Субстрати і ґрунти для рослин,Для розсади "
  },
  {
    "_id": "65a39ee40c56566a2624f7e0",
    "path": "Рослини і догляд за ними,Субстрати і ґрунти для рослин,Для садових рослин"
  },
  {
    "_id": "65a39ee40c56566a2624f7e1",
    "path": "Рослини і догляд за ними,Субстрати і ґрунти для рослин,Для тепличних рослин"
  },
  {
    "_id": "65a39ee40c56566a2624f7e2",
    "path": "Рослини і догляд за ними,Субстрати і ґрунти для рослин,Для хвойних і декоративних рослин"
  },
  {
    "_id": "65a39ee40c56566a2624f7e3",
    "path": "Рослини і догляд за ними,Субстрати і ґрунти для рослин,Для цибулинних"
  },
  {
    "_id": "65a39ee40c56566a2624f7e4",
    "path": "Рослини і догляд за ними,Субстрати і ґрунти для рослин,Для цитрусових"
  },
  {
    "_id": "65a39ee40c56566a2624f7e5",
    "path": "Рослини і догляд за ними,Субстрати і ґрунти для рослин,Універсальні"
  },
  {
    "_id": "65a39ee40c56566a2624f7e6",
    "path": "Рослини і догляд за ними,Садовий інвертар"
  },
  {
    "_id": "65a39ee40c56566a2624f7e7",
    "path": "Рослини і догляд за ними,Вазони"
  },
  {
    "_id": "65a39ee40c56566a2624f7e8",
    "path": "Рослини і догляд за ними,Засоби захисту рослин"
  },
  {
    "_id": "65a39ee40c56566a2624f7e9",
    "path": "Рослини і догляд за ними,Засоби захисту рослин,Інсектициди"
  },
  {
    "_id": "65a39ee40c56566a2624f7ea",
    "path": "Рослини і догляд за ними,Засоби захисту рослин,Фунгіциди"
  },
  {
    "_id": "65a39ee40c56566a2624f7eb",
    "path": "Рослини і догляд за ними,Засоби захисту рослин,Гербіциди"
  },
  {
    "_id": "65a39ee40c56566a2624f7ec",
    "path": "Рослини і догляд за ними,Засоби захисту рослин,Протруйники насіння"
  },
  {
    "_id": "65a39ee40c56566a2624f7ed",
    "path": "Рослини і догляд за ними,Засоби захисту рослин,Молюскоциди"
  },
  {
    "_id": "65a39ee40c56566a2624f7ee",
    "path": "Рослини і догляд за ними,Засоби захисту рослин,Прилипачі"
  },
  {
    "_id": "65a39ee40c56566a2624f7ef",
    "path": "Рослини і догляд за ними,Засоби захисту рослин,Десиканти"
  },
  {
    "_id": "65a39ee40c56566a2624f7f0",
    "path": "Рослини і догляд за ними,Добрива"
  },
  {
    "_id": "65a39ee40c56566a2624f7f1",
    "path": "Рослини і догляд за ними,Добрива,Мінеральні добрива"
  },
  {
    "_id": "65a39ee40c56566a2624f7f2",
    "path": "Рослини і догляд за ними,Добрива,Органічні добрива"
  },
  {
    "_id": "65a39ee40c56566a2624f7f3",
    "path": "Рослини і догляд за ними,Добрива,Стимулятори росту рослин"
  },
  {
    "_id": "65a39ee40c56566a2624f7f4",
    "path": "Рослини і догляд за ними,Добрива,Біодобрива"
  },
  {
    "_id": "65a39ee40c56566a2624f7f5",
    "path": "Рослини і догляд за ними,Добрива,Органомінеральні добрива"
  },
  {
    "_id": "65a39ee40c56566a2624f7f6",
    "path": "Рослини і догляд за ними,Добрива,Мікродобрива "
  },
  {
    "_id": "65a39ee40c56566a2624f7f7",
    "path": "Насіння"
  },
  {
    "_id": "65a39ee40c56566a2624f7f8",
    "path": "Насіння,Насіння овочів"
  },
  {
    "_id": "65a39ee40c56566a2624f7f9",
    "path": "Насіння,Насіння овочів,Насіння помідорів"
  },
  {
    "_id": "65a39ee40c56566a2624f7fa",
    "path": "Насіння,Насіння овочів,Насіння огірків"
  },
  {
    "_id": "65a39ee40c56566a2624f7fb",
    "path": "Насіння,Насіння овочів,Насіння перцю"
  },
  {
    "_id": "65a39ee40c56566a2624f7fc",
    "path": "Насіння,Насіння овочів,Насіння капусти"
  },
  {
    "_id": "65a39ee40c56566a2624f7fd",
    "path": "Насіння,Насіння овочів,Насіння цибулі"
  },
  {
    "_id": "65a39ee40c56566a2624f7fe",
    "path": "Насіння,Насіння овочів,Насіння кавуна"
  },
  {
    "_id": "65a39ee40c56566a2624f7ff",
    "path": "Насіння,Насіння овочів,Насіння моркви"
  },
  {
    "_id": "65a39ee40c56566a2624f800",
    "path": "Насіння,Насіння овочів,Насіння редиски"
  },
  {
    "_id": "65a39ee40c56566a2624f801",
    "path": "Насіння,Насіння овочів,Насіння гарбуза"
  },
  {
    "_id": "65a39ee40c56566a2624f802",
    "path": "Насіння,Насіння овочів,Насіння буряка"
  },
  {
    "_id": "65a39ee40c56566a2624f803",
    "path": "Насіння,Насіння овочів,Насіння кабачків"
  },
  {
    "_id": "65a39ee40c56566a2624f804",
    "path": "Насіння,Насіння овочів,Насіння баклажанів"
  },
  {
    "_id": "65a39ee40c56566a2624f805",
    "path": "Насіння,Насіння овочів,Насіння дині"
  },
  {
    "_id": "65a39ee40c56566a2624f806",
    "path": "Насіння,Насіння овочів,Насіння салату"
  },
  {
    "_id": "65a39ee40c56566a2624f807",
    "path": "Насіння,Насіння овочів,Насіння картоплі"
  },
  {
    "_id": "65a39ee40c56566a2624f808",
    "path": "Насіння,Насіння овочів,Насіння редьки"
  },
  {
    "_id": "65a39ee40c56566a2624f809",
    "path": "Насіння,Насіння овочів,Насіння патисонів"
  },
  {
    "_id": "65a39ee40c56566a2624f80a",
    "path": "Насіння,Насіння овочів,Насіння ріпи"
  },
  {
    "_id": "65a39ee40c56566a2624f80b",
    "path": "Насіння,Насіння овочів,Насіння артишоку"
  },
  {
    "_id": "65a39ee40c56566a2624f80c",
    "path": "Насіння,Насіння квітів"
  },
  {
    "_id": "65a39ee40c56566a2624f80d",
    "path": "Насіння,Насіння пряних і зелених трав"
  },
  {
    "_id": "65a39ee40c56566a2624f80e",
    "path": "Насіння,Насіння пряних і зелених трав,Насіння Щавелю"
  },
  {
    "_id": "65a39ee40c56566a2624f80f",
    "path": "Насіння,Насіння пряних і зелених трав,Насіння Базиліку"
  },
  {
    "_id": "65a39ee40c56566a2624f810",
    "path": "Насіння,Насіння бобових культур"
  },
  {
    "_id": "65a39ee40c56566a2624f811",
    "path": "Насіння,Насіння газонних трав"
  },
  {
    "_id": "65a39ee40c56566a2624f812",
    "path": "Насіння,Насіння сидератів і медоносів"
  },
  {
    "_id": "65a39ee40c56566a2624f813",
    "path": "Насіння,Насіння ягід"
  },
  {
    "_id": "65a39ee40c56566a2624f814",
    "path": "Насіння,Насіння зернових культур"
  },
  {
    "_id": "65a39ee40c56566a2624f815",
    "path": "Насіння,Насіння олійних культур"
  }
]
